{
	"required_textures":[
		"drpmedieval:argh/textures/textures/timbering.png",
		"drpmedieval:argh/textures/masks/timbering/double_diagonal_l_lr.png", "drpmedieval:argh/textures/overlays/timbering/double_diagonal_l_lr.png",
		"drpmedieval:argh/textures/masks/timbering/double_diagonal_r_lr.png", "drpmedieval:argh/textures/overlays/timbering/double_diagonal_r_lr.png",
		"drpmedieval:argh/textures/masks/timbering/double_diagonal_l_rl.png", "drpmedieval:argh/textures/overlays/timbering/double_diagonal_l_rl.png",
		"drpmedieval:argh/textures/masks/timbering/double_diagonal_r_rl.png", "drpmedieval:argh/textures/overlays/timbering/double_diagonal_r_rl.png"
	],
	"textures":[
		{"base":"clean_plank", "manipulations":[{"type":"mask","texture":"1"},{"type":"overlay","texture":"2"}], "cache":"%wood%_double_diagonal_l_lr"},
		{"base":"clean_plank", "manipulations":[{"type":"mask","texture":"3"},{"type":"overlay","texture":"4"}], "cache":"%wood%_double_diagonal_r_lr"},
		{"base":"clean_plank", "manipulations":[{"type":"mask","texture":"5"},{"type":"overlay","texture":"6"}], "cache":"%wood%_double_diagonal_l_rl"},
		{"base":"clean_plank", "manipulations":[{"type":"mask","texture":"7"},{"type":"overlay","texture":"8"}], "cache":"%wood%_double_diagonal_r_rl"},
	
		{"base":0, "manipulations":[{"type":"overlay","cached_texture":"%wood%_double_diagonal_l_lr"}], "output":"drpmedieval:textures/blocks/timbering/double_diagonal_l_lr/%wood%_timbering_0000"},
		{"base":0, "manipulations":[{"type":"overlay","cached_texture":"%wood%_double_diagonal_l_lr"}, {"type":"overlay","cached_texture":"%wood%_timbering_top"}], "output":"drpmedieval:textures/blocks/timbering/double_diagonal_l_lr/%wood%_timbering_1000"},
		{"base":0, "manipulations":[{"type":"overlay","cached_texture":"%wood%_double_diagonal_l_lr"}, {"type":"overlay","cached_texture":"%wood%_timbering_right"}], "output":"drpmedieval:textures/blocks/timbering/double_diagonal_l_lr/%wood%_timbering_0100"},
		{"base":0, "manipulations":[{"type":"overlay","cached_texture":"%wood%_double_diagonal_l_lr"}, {"type":"overlay","cached_texture":"%wood%_timbering_top"}, {"type":"overlay","cached_texture":"%wood%_timbering_right"}], "output":"drpmedieval:textures/blocks/timbering/double_diagonal_l_lr/%wood%_timbering_1100"},
		{"base":0, "manipulations":[{"type":"overlay","cached_texture":"%wood%_double_diagonal_l_lr"}, {"type":"overlay","cached_texture":"%wood%_timbering_bottom"}], "output":"drpmedieval:textures/blocks/timbering/double_diagonal_l_lr/%wood%_timbering_0010"},
		{"base":0, "manipulations":[{"type":"overlay","cached_texture":"%wood%_double_diagonal_l_lr"}, {"type":"overlay","cached_texture":"%wood%_timbering_top"}, {"type":"overlay","cached_texture":"%wood%_timbering_bottom"}], "output":"drpmedieval:textures/blocks/timbering/double_diagonal_l_lr/%wood%_timbering_1010"},
		{"base":0, "manipulations":[{"type":"overlay","cached_texture":"%wood%_double_diagonal_l_lr"}, {"type":"overlay","cached_texture":"%wood%_timbering_right"}, {"type":"overlay","cached_texture":"%wood%_timbering_bottom"}], "output":"drpmedieval:textures/blocks/timbering/double_diagonal_l_lr/%wood%_timbering_0110"},
		{"base":0, "manipulations":[{"type":"overlay","cached_texture":"%wood%_double_diagonal_l_lr"}, {"type":"overlay","cached_texture":"%wood%_timbering_top"}, {"type":"overlay","cached_texture":"%wood%_timbering_right"}, {"type":"overlay","cached_texture":"%wood%_timbering_bottom"}], "output":"drpmedieval:textures/blocks/timbering/double_diagonal_l_lr/%wood%_timbering_1110"},
		{"base":0, "manipulations":[{"type":"overlay","cached_texture":"%wood%_double_diagonal_l_lr"}, {"type":"overlay","cached_texture":"%wood%_timbering_left"}], "output":"drpmedieval:textures/blocks/timbering/double_diagonal_l_lr/%wood%_timbering_0001"},
		{"base":0, "manipulations":[{"type":"overlay","cached_texture":"%wood%_double_diagonal_l_lr"}, {"type":"overlay","cached_texture":"%wood%_timbering_top"}, {"type":"overlay","cached_texture":"%wood%_timbering_left"}], "output":"drpmedieval:textures/blocks/timbering/double_diagonal_l_lr/%wood%_timbering_1001"},
		{"base":0, "manipulations":[{"type":"overlay","cached_texture":"%wood%_double_diagonal_l_lr"}, {"type":"overlay","cached_texture":"%wood%_timbering_right"}, {"type":"overlay","cached_texture":"%wood%_timbering_left"}], "output":"drpmedieval:textures/blocks/timbering/double_diagonal_l_lr/%wood%_timbering_0101"},
		{"base":0, "manipulations":[{"type":"overlay","cached_texture":"%wood%_double_diagonal_l_lr"}, {"type":"overlay","cached_texture":"%wood%_timbering_top"}, {"type":"overlay","cached_texture":"%wood%_timbering_right"}, {"type":"overlay","cached_texture":"%wood%_timbering_left"}], "output":"drpmedieval:textures/blocks/timbering/double_diagonal_l_lr/%wood%_timbering_1101"},
		{"base":0, "manipulations":[{"type":"overlay","cached_texture":"%wood%_double_diagonal_l_lr"}, {"type":"overlay","cached_texture":"%wood%_timbering_bottom"}, {"type":"overlay","cached_texture":"%wood%_timbering_left"}], "output":"drpmedieval:textures/blocks/timbering/double_diagonal_l_lr/%wood%_timbering_0011"},
		{"base":0, "manipulations":[{"type":"overlay","cached_texture":"%wood%_double_diagonal_l_lr"}, {"type":"overlay","cached_texture":"%wood%_timbering_top"}, {"type":"overlay","cached_texture":"%wood%_timbering_bottom"}, {"type":"overlay","cached_texture":"%wood%_timbering_left"}], "output":"drpmedieval:textures/blocks/timbering/double_diagonal_l_lr/%wood%_timbering_1011"},
		{"base":0, "manipulations":[{"type":"overlay","cached_texture":"%wood%_double_diagonal_l_lr"}, {"type":"overlay","cached_texture":"%wood%_timbering_right"}, {"type":"overlay","cached_texture":"%wood%_timbering_bottom"}, {"type":"overlay","cached_texture":"%wood%_timbering_left"}], "output":"drpmedieval:textures/blocks/timbering/double_diagonal_l_lr/%wood%_timbering_0111"},
		{"base":0, "manipulations":[{"type":"overlay","cached_texture":"%wood%_double_diagonal_l_lr"}, {"type":"overlay","cached_texture":"%wood%_timbering_top"}, {"type":"overlay","cached_texture":"%wood%_timbering_right"}, {"type":"overlay","cached_texture":"%wood%_timbering_bottom"}, {"type":"overlay","cached_texture":"%wood%_timbering_left"}], "output":"drpmedieval:textures/blocks/timbering/double_diagonal_l_lr/%wood%_timbering_1111"},
	
		{"base":0, "manipulations":[{"type":"overlay","cached_texture":"%wood%_double_diagonal_r_lr"}], "output":"drpmedieval:textures/blocks/timbering/double_diagonal_r_lr/%wood%_timbering_0000"},
		{"base":0, "manipulations":[{"type":"overlay","cached_texture":"%wood%_double_diagonal_r_lr"}, {"type":"overlay","cached_texture":"%wood%_timbering_top"}], "output":"drpmedieval:textures/blocks/timbering/double_diagonal_r_lr/%wood%_timbering_1000"},
		{"base":0, "manipulations":[{"type":"overlay","cached_texture":"%wood%_double_diagonal_r_lr"}, {"type":"overlay","cached_texture":"%wood%_timbering_right"}], "output":"drpmedieval:textures/blocks/timbering/double_diagonal_r_lr/%wood%_timbering_0100"},
		{"base":0, "manipulations":[{"type":"overlay","cached_texture":"%wood%_double_diagonal_r_lr"}, {"type":"overlay","cached_texture":"%wood%_timbering_top"}, {"type":"overlay","cached_texture":"%wood%_timbering_right"}], "output":"drpmedieval:textures/blocks/timbering/double_diagonal_r_lr/%wood%_timbering_1100"},
		{"base":0, "manipulations":[{"type":"overlay","cached_texture":"%wood%_double_diagonal_r_lr"}, {"type":"overlay","cached_texture":"%wood%_timbering_bottom"}], "output":"drpmedieval:textures/blocks/timbering/double_diagonal_r_lr/%wood%_timbering_0010"},
		{"base":0, "manipulations":[{"type":"overlay","cached_texture":"%wood%_double_diagonal_r_lr"}, {"type":"overlay","cached_texture":"%wood%_timbering_top"}, {"type":"overlay","cached_texture":"%wood%_timbering_bottom"}], "output":"drpmedieval:textures/blocks/timbering/double_diagonal_r_lr/%wood%_timbering_1010"},
		{"base":0, "manipulations":[{"type":"overlay","cached_texture":"%wood%_double_diagonal_r_lr"}, {"type":"overlay","cached_texture":"%wood%_timbering_right"}, {"type":"overlay","cached_texture":"%wood%_timbering_bottom"}], "output":"drpmedieval:textures/blocks/timbering/double_diagonal_r_lr/%wood%_timbering_0110"},
		{"base":0, "manipulations":[{"type":"overlay","cached_texture":"%wood%_double_diagonal_r_lr"}, {"type":"overlay","cached_texture":"%wood%_timbering_top"}, {"type":"overlay","cached_texture":"%wood%_timbering_right"}, {"type":"overlay","cached_texture":"%wood%_timbering_bottom"}], "output":"drpmedieval:textures/blocks/timbering/double_diagonal_r_lr/%wood%_timbering_1110"},
		{"base":0, "manipulations":[{"type":"overlay","cached_texture":"%wood%_double_diagonal_r_lr"}, {"type":"overlay","cached_texture":"%wood%_timbering_left"}], "output":"drpmedieval:textures/blocks/timbering/double_diagonal_r_lr/%wood%_timbering_0001"},
		{"base":0, "manipulations":[{"type":"overlay","cached_texture":"%wood%_double_diagonal_r_lr"}, {"type":"overlay","cached_texture":"%wood%_timbering_top"}, {"type":"overlay","cached_texture":"%wood%_timbering_left"}], "output":"drpmedieval:textures/blocks/timbering/double_diagonal_r_lr/%wood%_timbering_1001"},
		{"base":0, "manipulations":[{"type":"overlay","cached_texture":"%wood%_double_diagonal_r_lr"}, {"type":"overlay","cached_texture":"%wood%_timbering_right"}, {"type":"overlay","cached_texture":"%wood%_timbering_left"}], "output":"drpmedieval:textures/blocks/timbering/double_diagonal_r_lr/%wood%_timbering_0101"},
		{"base":0, "manipulations":[{"type":"overlay","cached_texture":"%wood%_double_diagonal_r_lr"}, {"type":"overlay","cached_texture":"%wood%_timbering_top"}, {"type":"overlay","cached_texture":"%wood%_timbering_right"}, {"type":"overlay","cached_texture":"%wood%_timbering_left"}], "output":"drpmedieval:textures/blocks/timbering/double_diagonal_r_lr/%wood%_timbering_1101"},
		{"base":0, "manipulations":[{"type":"overlay","cached_texture":"%wood%_double_diagonal_r_lr"}, {"type":"overlay","cached_texture":"%wood%_timbering_bottom"}, {"type":"overlay","cached_texture":"%wood%_timbering_left"}], "output":"drpmedieval:textures/blocks/timbering/double_diagonal_r_lr/%wood%_timbering_0011"},
		{"base":0, "manipulations":[{"type":"overlay","cached_texture":"%wood%_double_diagonal_r_lr"}, {"type":"overlay","cached_texture":"%wood%_timbering_top"}, {"type":"overlay","cached_texture":"%wood%_timbering_bottom"}, {"type":"overlay","cached_texture":"%wood%_timbering_left"}], "output":"drpmedieval:textures/blocks/timbering/double_diagonal_r_lr/%wood%_timbering_1011"},
		{"base":0, "manipulations":[{"type":"overlay","cached_texture":"%wood%_double_diagonal_r_lr"}, {"type":"overlay","cached_texture":"%wood%_timbering_right"}, {"type":"overlay","cached_texture":"%wood%_timbering_bottom"}, {"type":"overlay","cached_texture":"%wood%_timbering_left"}], "output":"drpmedieval:textures/blocks/timbering/double_diagonal_r_lr/%wood%_timbering_0111"},
		{"base":0, "manipulations":[{"type":"overlay","cached_texture":"%wood%_double_diagonal_r_lr"}, {"type":"overlay","cached_texture":"%wood%_timbering_top"}, {"type":"overlay","cached_texture":"%wood%_timbering_right"}, {"type":"overlay","cached_texture":"%wood%_timbering_bottom"}, {"type":"overlay","cached_texture":"%wood%_timbering_left"}], "output":"drpmedieval:textures/blocks/timbering/double_diagonal_r_lr/%wood%_timbering_1111"},
			
		{"base":0, "manipulations":[{"type":"overlay","cached_texture":"%wood%_double_diagonal_l_rl"}], "output":"drpmedieval:textures/blocks/timbering/double_diagonal_l_rl/%wood%_timbering_0000"},
		{"base":0, "manipulations":[{"type":"overlay","cached_texture":"%wood%_double_diagonal_l_rl"}, {"type":"overlay","cached_texture":"%wood%_timbering_top"}], "output":"drpmedieval:textures/blocks/timbering/double_diagonal_l_rl/%wood%_timbering_1000"},
		{"base":0, "manipulations":[{"type":"overlay","cached_texture":"%wood%_double_diagonal_l_rl"}, {"type":"overlay","cached_texture":"%wood%_timbering_right"}], "output":"drpmedieval:textures/blocks/timbering/double_diagonal_l_rl/%wood%_timbering_0100"},
		{"base":0, "manipulations":[{"type":"overlay","cached_texture":"%wood%_double_diagonal_l_rl"}, {"type":"overlay","cached_texture":"%wood%_timbering_top"}, {"type":"overlay","cached_texture":"%wood%_timbering_right"}], "output":"drpmedieval:textures/blocks/timbering/double_diagonal_l_rl/%wood%_timbering_1100"},
		{"base":0, "manipulations":[{"type":"overlay","cached_texture":"%wood%_double_diagonal_l_rl"}, {"type":"overlay","cached_texture":"%wood%_timbering_bottom"}], "output":"drpmedieval:textures/blocks/timbering/double_diagonal_l_rl/%wood%_timbering_0010"},
		{"base":0, "manipulations":[{"type":"overlay","cached_texture":"%wood%_double_diagonal_l_rl"}, {"type":"overlay","cached_texture":"%wood%_timbering_top"}, {"type":"overlay","cached_texture":"%wood%_timbering_bottom"}], "output":"drpmedieval:textures/blocks/timbering/double_diagonal_l_rl/%wood%_timbering_1010"},
		{"base":0, "manipulations":[{"type":"overlay","cached_texture":"%wood%_double_diagonal_l_rl"}, {"type":"overlay","cached_texture":"%wood%_timbering_right"}, {"type":"overlay","cached_texture":"%wood%_timbering_bottom"}], "output":"drpmedieval:textures/blocks/timbering/double_diagonal_l_rl/%wood%_timbering_0110"},
		{"base":0, "manipulations":[{"type":"overlay","cached_texture":"%wood%_double_diagonal_l_rl"}, {"type":"overlay","cached_texture":"%wood%_timbering_top"}, {"type":"overlay","cached_texture":"%wood%_timbering_right"}, {"type":"overlay","cached_texture":"%wood%_timbering_bottom"}], "output":"drpmedieval:textures/blocks/timbering/double_diagonal_l_rl/%wood%_timbering_1110"},
		{"base":0, "manipulations":[{"type":"overlay","cached_texture":"%wood%_double_diagonal_l_rl"}, {"type":"overlay","cached_texture":"%wood%_timbering_left"}], "output":"drpmedieval:textures/blocks/timbering/double_diagonal_l_rl/%wood%_timbering_0001"},
		{"base":0, "manipulations":[{"type":"overlay","cached_texture":"%wood%_double_diagonal_l_rl"}, {"type":"overlay","cached_texture":"%wood%_timbering_top"}, {"type":"overlay","cached_texture":"%wood%_timbering_left"}], "output":"drpmedieval:textures/blocks/timbering/double_diagonal_l_rl/%wood%_timbering_1001"},
		{"base":0, "manipulations":[{"type":"overlay","cached_texture":"%wood%_double_diagonal_l_rl"}, {"type":"overlay","cached_texture":"%wood%_timbering_right"}, {"type":"overlay","cached_texture":"%wood%_timbering_left"}], "output":"drpmedieval:textures/blocks/timbering/double_diagonal_l_rl/%wood%_timbering_0101"},
		{"base":0, "manipulations":[{"type":"overlay","cached_texture":"%wood%_double_diagonal_l_rl"}, {"type":"overlay","cached_texture":"%wood%_timbering_top"}, {"type":"overlay","cached_texture":"%wood%_timbering_right"}, {"type":"overlay","cached_texture":"%wood%_timbering_left"}], "output":"drpmedieval:textures/blocks/timbering/double_diagonal_l_rl/%wood%_timbering_1101"},
		{"base":0, "manipulations":[{"type":"overlay","cached_texture":"%wood%_double_diagonal_l_rl"}, {"type":"overlay","cached_texture":"%wood%_timbering_bottom"}, {"type":"overlay","cached_texture":"%wood%_timbering_left"}], "output":"drpmedieval:textures/blocks/timbering/double_diagonal_l_rl/%wood%_timbering_0011"},
		{"base":0, "manipulations":[{"type":"overlay","cached_texture":"%wood%_double_diagonal_l_rl"}, {"type":"overlay","cached_texture":"%wood%_timbering_top"}, {"type":"overlay","cached_texture":"%wood%_timbering_bottom"}, {"type":"overlay","cached_texture":"%wood%_timbering_left"}], "output":"drpmedieval:textures/blocks/timbering/double_diagonal_l_rl/%wood%_timbering_1011"},
		{"base":0, "manipulations":[{"type":"overlay","cached_texture":"%wood%_double_diagonal_l_rl"}, {"type":"overlay","cached_texture":"%wood%_timbering_right"}, {"type":"overlay","cached_texture":"%wood%_timbering_bottom"}, {"type":"overlay","cached_texture":"%wood%_timbering_left"}], "output":"drpmedieval:textures/blocks/timbering/double_diagonal_l_rl/%wood%_timbering_0111"},
		{"base":0, "manipulations":[{"type":"overlay","cached_texture":"%wood%_double_diagonal_l_rl"}, {"type":"overlay","cached_texture":"%wood%_timbering_top"}, {"type":"overlay","cached_texture":"%wood%_timbering_right"}, {"type":"overlay","cached_texture":"%wood%_timbering_bottom"}, {"type":"overlay","cached_texture":"%wood%_timbering_left"}], "output":"drpmedieval:textures/blocks/timbering/double_diagonal_l_rl/%wood%_timbering_1111"},
		
		{"base":0, "manipulations":[{"type":"overlay","cached_texture":"%wood%_double_diagonal_r_rl"}], "output":"drpmedieval:textures/blocks/timbering/double_diagonal_r_rl/%wood%_timbering_0000"},
		{"base":0, "manipulations":[{"type":"overlay","cached_texture":"%wood%_double_diagonal_r_rl"}, {"type":"overlay","cached_texture":"%wood%_timbering_top"}], "output":"drpmedieval:textures/blocks/timbering/double_diagonal_r_rl/%wood%_timbering_1000"},
		{"base":0, "manipulations":[{"type":"overlay","cached_texture":"%wood%_double_diagonal_r_rl"}, {"type":"overlay","cached_texture":"%wood%_timbering_right"}], "output":"drpmedieval:textures/blocks/timbering/double_diagonal_r_rl/%wood%_timbering_0100"},
		{"base":0, "manipulations":[{"type":"overlay","cached_texture":"%wood%_double_diagonal_r_rl"}, {"type":"overlay","cached_texture":"%wood%_timbering_top"}, {"type":"overlay","cached_texture":"%wood%_timbering_right"}], "output":"drpmedieval:textures/blocks/timbering/double_diagonal_r_rl/%wood%_timbering_1100"},
		{"base":0, "manipulations":[{"type":"overlay","cached_texture":"%wood%_double_diagonal_r_rl"}, {"type":"overlay","cached_texture":"%wood%_timbering_bottom"}], "output":"drpmedieval:textures/blocks/timbering/double_diagonal_r_rl/%wood%_timbering_0010"},
		{"base":0, "manipulations":[{"type":"overlay","cached_texture":"%wood%_double_diagonal_r_rl"}, {"type":"overlay","cached_texture":"%wood%_timbering_top"}, {"type":"overlay","cached_texture":"%wood%_timbering_bottom"}], "output":"drpmedieval:textures/blocks/timbering/double_diagonal_r_rl/%wood%_timbering_1010"},
		{"base":0, "manipulations":[{"type":"overlay","cached_texture":"%wood%_double_diagonal_r_rl"}, {"type":"overlay","cached_texture":"%wood%_timbering_right"}, {"type":"overlay","cached_texture":"%wood%_timbering_bottom"}], "output":"drpmedieval:textures/blocks/timbering/double_diagonal_r_rl/%wood%_timbering_0110"},
		{"base":0, "manipulations":[{"type":"overlay","cached_texture":"%wood%_double_diagonal_r_rl"}, {"type":"overlay","cached_texture":"%wood%_timbering_top"}, {"type":"overlay","cached_texture":"%wood%_timbering_right"}, {"type":"overlay","cached_texture":"%wood%_timbering_bottom"}], "output":"drpmedieval:textures/blocks/timbering/double_diagonal_r_rl/%wood%_timbering_1110"},
		{"base":0, "manipulations":[{"type":"overlay","cached_texture":"%wood%_double_diagonal_r_rl"}, {"type":"overlay","cached_texture":"%wood%_timbering_left"}], "output":"drpmedieval:textures/blocks/timbering/double_diagonal_r_rl/%wood%_timbering_0001"},
		{"base":0, "manipulations":[{"type":"overlay","cached_texture":"%wood%_double_diagonal_r_rl"}, {"type":"overlay","cached_texture":"%wood%_timbering_top"}, {"type":"overlay","cached_texture":"%wood%_timbering_left"}], "output":"drpmedieval:textures/blocks/timbering/double_diagonal_r_rl/%wood%_timbering_1001"},
		{"base":0, "manipulations":[{"type":"overlay","cached_texture":"%wood%_double_diagonal_r_rl"}, {"type":"overlay","cached_texture":"%wood%_timbering_right"}, {"type":"overlay","cached_texture":"%wood%_timbering_left"}], "output":"drpmedieval:textures/blocks/timbering/double_diagonal_r_rl/%wood%_timbering_0101"},
		{"base":0, "manipulations":[{"type":"overlay","cached_texture":"%wood%_double_diagonal_r_rl"}, {"type":"overlay","cached_texture":"%wood%_timbering_top"}, {"type":"overlay","cached_texture":"%wood%_timbering_right"}, {"type":"overlay","cached_texture":"%wood%_timbering_left"}], "output":"drpmedieval:textures/blocks/timbering/double_diagonal_r_rl/%wood%_timbering_1101"},
		{"base":0, "manipulations":[{"type":"overlay","cached_texture":"%wood%_double_diagonal_r_rl"}, {"type":"overlay","cached_texture":"%wood%_timbering_bottom"}, {"type":"overlay","cached_texture":"%wood%_timbering_left"}], "output":"drpmedieval:textures/blocks/timbering/double_diagonal_r_rl/%wood%_timbering_0011"},
		{"base":0, "manipulations":[{"type":"overlay","cached_texture":"%wood%_double_diagonal_r_rl"}, {"type":"overlay","cached_texture":"%wood%_timbering_top"}, {"type":"overlay","cached_texture":"%wood%_timbering_bottom"}, {"type":"overlay","cached_texture":"%wood%_timbering_left"}], "output":"drpmedieval:textures/blocks/timbering/double_diagonal_r_rl/%wood%_timbering_1011"},
		{"base":0, "manipulations":[{"type":"overlay","cached_texture":"%wood%_double_diagonal_r_rl"}, {"type":"overlay","cached_texture":"%wood%_timbering_right"}, {"type":"overlay","cached_texture":"%wood%_timbering_bottom"}, {"type":"overlay","cached_texture":"%wood%_timbering_left"}], "output":"drpmedieval:textures/blocks/timbering/double_diagonal_r_rl/%wood%_timbering_0111"},
		{"base":0, "manipulations":[{"type":"overlay","cached_texture":"%wood%_double_diagonal_r_rl"}, {"type":"overlay","cached_texture":"%wood%_timbering_top"}, {"type":"overlay","cached_texture":"%wood%_timbering_right"}, {"type":"overlay","cached_texture":"%wood%_timbering_bottom"}, {"type":"overlay","cached_texture":"%wood%_timbering_left"}], "output":"drpmedieval:textures/blocks/timbering/double_diagonal_r_rl/%wood%_timbering_1111"}
	
	
	]
}